xs_transformers/__init__.py
xs_transformers/activations.py
xs_transformers/activations_tf.py
xs_transformers/configuration_utils.py
xs_transformers/convert_graph_to_onnx.py
xs_transformers/convert_pytorch_checkpoint_to_tf2.py
xs_transformers/convert_slow_tokenizer.py
xs_transformers/convert_slow_tokenizers_checkpoints_to_fast.py
xs_transformers/convert_tf_hub_seq_to_seq_bert_to_pytorch.py
xs_transformers/debug_utils.py
xs_transformers/deepspeed.py
xs_transformers/dependency_versions_check.py
xs_transformers/dependency_versions_table.py
xs_transformers/dynamic_module_utils.py
xs_transformers/feature_extraction_sequence_utils.py
xs_transformers/feature_extraction_utils.py
xs_transformers/file_utils.py
xs_transformers/generation_beam_constraints.py
xs_transformers/generation_beam_search.py
xs_transformers/generation_flax_logits_process.py
xs_transformers/generation_flax_utils.py
xs_transformers/generation_logits_process.py
xs_transformers/generation_stopping_criteria.py
xs_transformers/generation_tf_logits_process.py
xs_transformers/generation_tf_utils.py
xs_transformers/generation_utils.py
xs_transformers/hf_argparser.py
xs_transformers/image_processing_utils.py
xs_transformers/image_transforms.py
xs_transformers/image_utils.py
xs_transformers/integrations.py
xs_transformers/keras_callbacks.py
xs_transformers/modelcard.py
xs_transformers/modeling_flax_outputs.py
xs_transformers/modeling_flax_pytorch_utils.py
xs_transformers/modeling_flax_utils.py
xs_transformers/modeling_outputs.py
xs_transformers/modeling_tf_outputs.py
xs_transformers/modeling_tf_pytorch_utils.py
xs_transformers/modeling_tf_utils.py
xs_transformers/modeling_utils.py
xs_transformers/optimization.py
xs_transformers/optimization_tf.py
xs_transformers/processing_utils.py
xs_transformers/pytorch_utils.py
xs_transformers/testing_utils.py
xs_transformers/tf_utils.py
xs_transformers/tokenization_utils.py
xs_transformers/tokenization_utils_base.py
xs_transformers/tokenization_utils_fast.py
xs_transformers-1.0.7.dist-info/METADATA
xs_transformers-1.0.7.dist-info/WHEEL
xs_transformers-1.0.7.dist-info/top_level.txt
xs_transformers-1.0.7.dist-info/RECORD
