Metadata-Version: 2.1
Name: xs-transformers
Version: 1.0.7
Summary: xs transformers from transformers
Home-page: UNKNOWN
License: UNKNOWN
Platform: UNKNOWN
Requires-Python: >=3
